winpwn/__init__.py
winpwn/context.py
winpwn/dbg.py
winpwn/misc.py
winpwn/var.py
winpwn/win.py
winpwn/winpwn.py
letpwn-0.0.1.dist-info/METADATA
letpwn-0.0.1.dist-info/WHEEL
letpwn-0.0.1.dist-info/top_level.txt
letpwn-0.0.1.dist-info/RECORD
